recursivenodes/__init__.py
recursivenodes/conftest.py
recursivenodes/lebesgue.py
recursivenodes/lebesgue_constants.csv
recursivenodes/metrics.py
recursivenodes/more_lebesgue_constants.csv
recursivenodes/nodes.py
recursivenodes/polynomials.py
recursivenodes/quadrature.py
recursivenodes/utils.py
recursivenodes-0.2.0.dist-info/LICENSE
recursivenodes-0.2.0.dist-info/METADATA
recursivenodes-0.2.0.dist-info/WHEEL
recursivenodes-0.2.0.dist-info/top_level.txt
recursivenodes-0.2.0.dist-info/RECORD
