Metadata-Version: 2.1
Name: recursivenodes
Version: 0.2.0
Summary: Recursively defined interpolation nodes for the simplex
Home-page: https://tisaac.gitlab.io/recursivenodes/
Author: Toby Isaac
Author-email: tisaac@cc.gatech.edu
License: MIT
Project-URL: Bug Tracker, https://gitlab.com/tisaac/recursivenodes/issues
Project-URL: Source Code, https://gitlab.com/tisaac/recursivenodes/
Platform: UNKNOWN
Classifier: Programming Language :: Python :: 3
Classifier: License :: OSI Approved :: MIT License
Classifier: Operating System :: OS Independent
Classifier: Intended Audience :: Science/Research
Classifier: Natural Language :: English
Classifier: Topic :: Scientific/Engineering :: Mathematics
Requires-Python: >=3.6
Provides-Extra: test
Provides-Extra: doc
Provides-Extra: lebesgue
Provides-Extra: all
